discordbotlinuxmonitor/__init__.py
discordbotlinuxmonitor/__main__.py
discordbotlinuxmonitor/discordbotlinuxmonitor.py
DiscordBotLinuxMonitor-1.5.1.dist-info/LICENSE.md
DiscordBotLinuxMonitor-1.5.1.dist-info/METADATA
DiscordBotLinuxMonitor-1.5.1.dist-info/WHEEL
DiscordBotLinuxMonitor-1.5.1.dist-info/top_level.txt
DiscordBotLinuxMonitor-1.5.1.dist-info/RECORD
