Metadata-Version: 2.1
Name: DiscordBotLinuxMonitor
Version: 1.5.1
Summary: From discord channels: Get information and warning status of Linux server like service, port, ping, ssl certificate, disk/folder/cpu/ram/swap usage, ip connection, ... (Python and shell library, Linux ONLY)
Home-page: https://github.com/QuentinCG/Discord-Bot-Linux-Monitor-Python-Library
Author: Quentin Comte-Gaz
Author-email: quentin@comte-gaz.com
License: MIT
Keywords: discord bot warning info linux monitor monitoring server service port ping ssl certificate disk folder cpu ram swap usage ip connection
Platform: Linux
Classifier: Programming Language :: Python :: 3 :: Only
Classifier: License :: OSI Approved :: MIT License
Classifier: Operating System :: POSIX :: Linux
Classifier: Natural Language :: English
Classifier: Intended Audience :: Developers
Classifier: Intended Audience :: System Administrators
Classifier: Topic :: System :: Monitoring
Classifier: Topic :: System :: Networking :: Monitoring
Classifier: Topic :: System :: Systems Administration
Classifier: Development Status :: 5 - Production/Stable
Classifier: Environment :: Console
Requires-Python: >=3.3
License-File: LICENSE.md
Requires-Dist: linuxmonitor ~=1.5.0
Requires-Dist: discord.py
Requires-Dist: typing
Requires-Dist: asyncio
